{
    "instance": "i-00000000000000000",
    "command": "aaaaaaaa-1111-4444-0000-999999999999",
    "input": "groupname/inputs/dataset.ext",
    "status": "SUCCESS",
    "reason": 0,
    "memory_usage": "8192 MB",
    "cpu_usage": "20.4 %",
    "job_start": "2021-05-13T23:02:55Z",
    "job_finish": "2021-05-13T23:02:56Z",
    "std": {
        "0": "Thu May 13 23:02:55 EDT 2021\n",
        "1": "Thu May 13 23:02:55 EDT 2021\n",
        "2": "Thu May 13 23:02:56 EDT 2021\n",
        "3": "Thu May 13 23:02:56 EDT 2021\n",
        "4": "Thu May 13 23:02:56 EDT 2021\n"
    }
}