{
    "user_root_dir":"/Users/taigaabe",
    "conda_dir":"/Users/taigaabe/anaconda3/bin",
    "script_name":"example.sh",
    "env_name":"neurocaas",
    "in":{
        "data":{
                "local_location":"/home/ubuntu/datastore/",
                "ext":[".mpg",".mp4"]
               },
        "config":{
                "local_location":"/home/ubuntu/datastore/",
                "ext":[".json",".yaml"]
               }
        },
    "out":{
        "out1":{
                "local_location":"/home/ubuntu/outstore/results"
            }
        },
    "dlami":true
}
